{
  "proto_counts": [
    0,
    0,
    0,
    0,
    0,
    0,
    0,
    0,
    0,
    1004,
    0,
    0,
    0,
    0,
    0,
    0
  ],
  "proto_avg_scores": [
    0.0,
    0.0,
    0.0,
    0.0,
    0.0,
    0.0,
    0.0,
    0.0,
    0.0,
    0.1981201171875,
    0.0,
    0.0,
    0.0,
    0.0,
    0.0,
    0.0
  ],
  "high_score_proto_counts": [
    0,
    0,
    0,
    0,
    0,
    0,
    0,
    0,
    0,
    201,
    0,
    0,
    0,
    0,
    0,
    0
  ],
  "high_score_threshold": 0.206103515625,
  "top5_bad_prototypes": [
    {
      "index": 9,
      "count": 1004,
      "high_score_count": 201,
      "avg_score": 0.1981201171875
    },
    {
      "index": 15,
      "count": 0,
      "high_score_count": 0,
      "avg_score": 0.0
    },
    {
      "index": 14,
      "count": 0,
      "high_score_count": 0,
      "avg_score": 0.0
    },
    {
      "index": 13,
      "count": 0,
      "high_score_count": 0,
      "avg_score": 0.0
    },
    {
      "index": 12,
      "count": 0,
      "high_score_count": 0,
      "avg_score": 0.0
    }
  ]
}